friendly_data/__init__.py
friendly_data/__main__.py
friendly_data/_types.py
friendly_data/cli.py
friendly_data/converters.py
friendly_data/dpkg.py
friendly_data/helpers.py
friendly_data/iamc.py
friendly_data/io.py
friendly_data/metatools.py
friendly_data/py.typed
friendly_data/registry.py
friendly_data/tseries.py
friendly_data/validate.py
friendly_data/doc/__init__.py
friendly_data/doc/__main__.py
friendly_data/doc/dpkg_describe.template
friendly_data/doc/entry.md.template
friendly_data/doc/entry.rst.template
friendly_data/doc/index.html.template
friendly_data/doc/page.md.template
friendly_data/doc/page.rst.template
friendly_data-0.3.3.dist-info/LICENSE
friendly_data-0.3.3.dist-info/METADATA
friendly_data-0.3.3.dist-info/WHEEL
friendly_data-0.3.3.dist-info/entry_points.txt
friendly_data-0.3.3.dist-info/top_level.txt
friendly_data-0.3.3.dist-info/RECORD
