Metadata-Version: 2.1
Name: friendly-data
Version: 0.3.3
Summary: A frictionless data package implementation for energy system data.
Home-page: https://github.com/sentinel-energy/friendly_data
License: UNKNOWN
Platform: UNKNOWN
License-File: LICENSE
Requires-Dist: fire
Requires-Dist: frictionless (<4.1,>=4.0.2)
Requires-Dist: friendly-data-registry
Requires-Dist: glom (>=19.10)
Requires-Dist: jinja2
Requires-Dist: numexpr
Requires-Dist: numpy
Requires-Dist: pandas (>=1.3)
Requires-Dist: pyyaml
Requires-Dist: requests
Requires-Dist: rich
Requires-Dist: tabulate
Requires-Dist: xarray
